pymanga/__init__.py
pymanga/api.py
pymanga/genres.py
pymanga/parsers/__init__.py
pymanga/parsers/adv_search_parser.py
pymanga/parsers/author_parsers.py
pymanga/parsers/group_parsers.py
pymanga/parsers/releases_parsers.py
pymanga/parsers/search_parsers.py
pymanga/parsers/series_parsers.py
pymanga/parsers/utils.py
py_manga-0.2.4.dist-info/LICENSE
py_manga-0.2.4.dist-info/METADATA
py_manga-0.2.4.dist-info/WHEEL
py_manga-0.2.4.dist-info/top_level.txt
py_manga-0.2.4.dist-info/RECORD
