Metadata-Version: 2.1
Name: py-manga
Version: 0.2.4
Summary: A library to get information from mangaupdates.com
Home-page: https://github.com/alisw/py-manga
Author: Allie
Author-email: allie@cat-girl.gay
Classifier: Programming Language :: Python :: 3
Classifier: License :: CC0 1.0 Universal (CC0 1.0) Public Domain Dedication
Classifier: Operating System :: OS Independent
Requires-Python: >=3.4
License-File: LICENSE
Requires-Dist: beautifulsoup4
Requires-Dist: requests
Requires-Dist: markdownify
Requires-Dist: html2text
